barid/__init__.py
barid/api/mailapi.py
barid/client/__init__.py
barid/client/domains/domains_list.py
barid/client/emails/emails_count.py
barid/client/emails/emails_delete.py
barid/client/emails/emails_list.py
barid/client/engine.py
barid/client/inbox/inbox_delete.py
barid/client/inbox/inbox_detail.py
barid/models/__init__.py
barid/models/delete.py
barid/models/details.py
barid/models/email.py
barid/types/__init__.py
barid/types/ctypes.py
barid/utils/decorators.py
barid/utils/session.py
barid-0.2.0.dist-info/LICENSE
barid-0.2.0.dist-info/METADATA
barid-0.2.0.dist-info/WHEEL
barid-0.2.0.dist-info/RECORD
