Metadata-Version: 2.3
Name: barid
Version: 0.2.0
Summary: A deeply abstract, fully asynchronous Python client for the Barid temporary email API with complex architecture and type-heavy design.
License: MIT
Author: Hexa
Requires-Python: >=3.8
Classifier: License :: OSI Approved :: MIT License
Classifier: Programming Language :: Python :: 3
Classifier: Programming Language :: Python :: 3.8
Classifier: Programming Language :: Python :: 3.9
Classifier: Programming Language :: Python :: 3.10
Classifier: Programming Language :: Python :: 3.11
Classifier: Programming Language :: Python :: 3.12
Classifier: Programming Language :: Python :: 3.13
Requires-Dist: email-validator
Requires-Dist: httpx[http2]
Requires-Dist: pydantic
